aiohttp_riak-0.0.1.dist-info/RECORD
aiohttp_riak-0.0.1.dist-info/WHEEL
aiohttp_riak-0.0.1.dist-info/METADATA
aiohttp_riak-0.0.1.dist-info/DESCRIPTION.rst
aiohttp_riak-0.0.1.dist-info/top_level.txt
aiohttp_riak-0.0.1.dist-info/metadata.json
aiohttp_riak/exc.py
aiohttp_riak/Bucket.py
aiohttp_riak/Client.py
aiohttp_riak/__init__.py
aiohttp_riak/Server.py
