Metadata-Version: 2.0
Name: aiohttp-riak
Version: 0.0.1
Summary: HTTP Riak connector for aiohttp
Home-page: https://github.com/zloidemon/aiohttp_riak/
Author: Veniamin Gvozdikov
Author-email: g.veniamin@googlemail.com
License: BSD
Keywords: aiohttp riak
Platform: any
Classifier: Intended Audience :: Developers
Classifier: License :: OSI Approved :: BSD License
Classifier: Programming Language :: Python :: 3
Classifier: Programming Language :: Python :: 3.5
Classifier: Programming Language :: Python
Classifier: Topic :: Internet :: WWW/HTTP
Requires-Dist: aiohttp (>=0.17)
